src/__init__.py
src/main.py
src/snippets/__init__.py
src/snippets/css.py
src/snippets/html.py
src/snippets/php.py
src/snippets/sass.py
src/vars/__init__.py
wp_tdk-0.0.1.dist-info/LICENSE
wp_tdk-0.0.1.dist-info/METADATA
wp_tdk-0.0.1.dist-info/WHEEL
wp_tdk-0.0.1.dist-info/entry_points.txt
wp_tdk-0.0.1.dist-info/top_level.txt
wp_tdk-0.0.1.dist-info/RECORD
