Metadata-Version: 2.1
Name: wp-tdk
Version: 0.0.1
Summary: Generates the boilerplate files for a custom wordpress theme
Home-page: https://github.com/matthewBeckwith/wp-tdk
Author: Matthew Beckwith
Author-email: kodahscripts@outlook.com
Classifier: Programming Language :: Python :: 3
Classifier: License :: OSI Approved :: MIT License
Classifier: Operating System :: OS Independent
Requires-Python: >=3.10
License-File: LICENSE
